<objects>
  <bricks>
    <brick x="64" y="320" widthbbox="64" heightbbox="32"/>
    <brick x="32" y="224" widthbbox="32" heightbbox="96"/>
    <brick x="160" y="320" widthbbox="32" heightbbox="32"/>
    <brick x="256" y="192" widthbbox="64" heightbbox="32"/>
    <brick x="288" y="224" widthbbox="32" heightbbox="32"/>
    <brick x="448" y="192" widthbbox="64" heightbbox="32"/>
    <brick x="320" y="320" widthbbox="320" heightbbox="32"/>
    <brick x="704" y="320" widthbbox="64" heightbbox="32"/>
    <brick x="832" y="256" widthbbox="64" heightbbox="32"/>
    <brick x="896" y="320" widthbbox="64" heightbbox="32"/>
    <brick x="960" y="224" widthbbox="64" heightbbox="32"/>
    <brick x="960" y="352" widthbbox="128" heightbbox="32"/>
    <brick x="1088" y="192" widthbbox="64" heightbbox="32"/>
    <brick x="1216" y="320" widthbbox="128" heightbbox="32"/>
    <brick x="1344" y="288" widthbbox="64" heightbbox="32"/>
    <brick x="1408" y="224" widthbbox="64" heightbbox="32"/>
    <brick x="1472" y="256" widthbbox="64" heightbbox="32"/>
  </bricks> 

  <stairs>
    <stair x="82" y="256" stairDirection="3"/>  
    <stair x="112" y="318" stairDirection="1"/>  
    <stair x="272" y="128" stairDirection="4"/>  
  </stairs>

  <enemies>
    <ghost x="192" y="80" beginPositionX="256" lastPositionX="1312" bboxEnemyWidth="30" bboxEnemyHeight="30" bboxEnemyActiveWidth="100" bboxEnemyActiveHeight="100"/>

    <skeletons>
      <skeleton x="720" y="254" beginPositionX="65" lastPositionX="284" bboxEnemyWidth="32" bboxEnemyHeight="64" bboxEnemyActiveWidth="200" bboxEnemyActiveHeight="100"/>
      <skeleton x="1289" y="254" beginPositionX="65" lastPositionX="284" bboxEnemyWidth="32" bboxEnemyHeight="64" bboxEnemyActiveWidth="200" bboxEnemyActiveHeight="100"/>
    </skeletons>

    <crows>
      <crow x="544" y="72" bboxEnemyWidth="32" bboxEnemyHeight="32" bboxEnemyActiveWidth="100" bboxEnemyActiveHeight="256"/>
      <crow x="1289" y="256" bboxEnemyWidth="32" bboxEnemyHeight="32" bboxEnemyActiveWidth="100" bboxEnemyActiveHeight="256"/>
    </corws>
  </enemies>
</objects>